resono/__init__.py
resono/aes.py
resono/cli.py
resono/phase_embed.py
resono/phase_extract.py
resono-1.0.1.dist-info/licenses/LICENSE
resono-1.0.1.dist-info/METADATA
resono-1.0.1.dist-info/WHEEL
resono-1.0.1.dist-info/entry_points.txt
resono-1.0.1.dist-info/top_level.txt
resono-1.0.1.dist-info/RECORD
