Metadata-Version: 2.4
Name: resono
Version: 1.0.1
Summary: Audio steganography tool using phase coding
Author-email: kaizoku73 <ultimate0134@gmail.com>
Maintainer-email: kaizoku73 <ultimate0134@gmail.com>
License: MIT
Project-URL: Homepage, https://github.com/kaizoku73/Resono
Project-URL: Repository, https://github.com/kaizoku73/Resono
Project-URL: Bug Reports, https://github.com/kaizoku73/Resono/issues
Project-URL: Documentation, https://kaizoku.gitbook.io/steganography/phase-coding-in-audio
Keywords: steganography,audio,phase-coding,cryptography,security,wav,phase-manipulation
Classifier: Development Status :: 5 - Production/Stable
Classifier: Intended Audience :: Developers
Classifier: Intended Audience :: End Users/Desktop
Classifier: Topic :: Security :: Cryptography
Classifier: Topic :: Multimedia :: Sound/Audio
Classifier: License :: OSI Approved :: MIT License
Classifier: Programming Language :: Python :: 3
Classifier: Programming Language :: Python :: 3.7
Classifier: Programming Language :: Python :: 3.8
Classifier: Programming Language :: Python :: 3.9
Classifier: Programming Language :: Python :: 3.10
Classifier: Programming Language :: Python :: 3.11
Classifier: Programming Language :: Python :: 3.12
Classifier: Operating System :: OS Independent
Requires-Python: >=3.7
License-File: LICENSE
Requires-Dist: numpy>=1.21.0
Requires-Dist: scipy>=1.7.0
Requires-Dist: pycryptodome>=3.15.0
Dynamic: license-file
